MANIFEST.in
README.txt
setup.py
setup.pyc
Products/__init__.py
Products/__init__.pyc
Products.ATSuccessStory.egg-info/PKG-INFO
Products.ATSuccessStory.egg-info/SOURCES.txt
Products.ATSuccessStory.egg-info/dependency_links.txt
Products.ATSuccessStory.egg-info/entry_points.txt
Products.ATSuccessStory.egg-info/namespace_packages.txt
Products.ATSuccessStory.egg-info/not-zip-safe
Products.ATSuccessStory.egg-info/requires.txt
Products.ATSuccessStory.egg-info/top_level.txt
Products/ATSuccessStory/__init__.py
Products/ATSuccessStory/__init__.pyc
Products/ATSuccessStory/config.py
Products/ATSuccessStory/config.pyc
Products/ATSuccessStory/configure.zcml
Products/ATSuccessStory/profiles.zcml
Products/ATSuccessStory/setuphandlers.py
Products/ATSuccessStory/setuphandlers.pyc
Products/ATSuccessStory/updates.zcml
Products/ATSuccessStory/vocabularies.py
Products/ATSuccessStory/vocabularies.pyc
Products/ATSuccessStory/browser/__init__.py
Products/ATSuccessStory/browser/__init__.pyc
Products/ATSuccessStory/browser/configure.zcml
Products/ATSuccessStory/browser/portlets/__init__.py
Products/ATSuccessStory/browser/portlets/__init__.pyc
Products/ATSuccessStory/browser/portlets/successstory.py
Products/ATSuccessStory/browser/portlets/successstory.pyc
Products/ATSuccessStory/browser/templates/portlet_success.pt
Products/ATSuccessStory/content/ATSuccessStory.py
Products/ATSuccessStory/content/ATSuccessStory.pyc
Products/ATSuccessStory/content/ATSuccessStoryFolder.py
Products/ATSuccessStory/content/ATSuccessStoryFolder.pyc
Products/ATSuccessStory/content/__init__.py
Products/ATSuccessStory/content/__init__.pyc
Products/ATSuccessStory/content/interfaces.py
Products/ATSuccessStory/content/interfaces.pyc
Products/ATSuccessStory/locales/ATSuccessStory.pot
Products/ATSuccessStory/locales/custom.pot
Products/ATSuccessStory/locales/es/LC_MESSAGES/ATSuccessStory.mo
Products/ATSuccessStory/locales/es/LC_MESSAGES/ATSuccessStory.po
Products/ATSuccessStory/locales/no/LC_MESSAGES/ATSuccessStory.mo
Products/ATSuccessStory/locales/no/LC_MESSAGES/ATSuccessStory.po
Products/ATSuccessStory/locales/sv/LC_MESSAGES/ATSuccessStory.mo
Products/ATSuccessStory/locales/sv/LC_MESSAGES/ATSuccessStory.po
Products/ATSuccessStory/profiles/default/ATSuccessStory_marker.txt
Products/ATSuccessStory/profiles/default/cssregistry.xml
Products/ATSuccessStory/profiles/default/factorytool.xml
