Metadata-Version: 1.1
Name: Products.ATSuccessStory
Version: 4.1.3
Summary: Success stories
Home-page: https://github.com/collective/Products.ATSuccessStory
Author: Franco Pellegrini
Author-email: frapell@gmail.com
License: GPL
Keywords: plone successstory
Platform: UNKNOWN
Classifier: Framework :: Plone
Classifier: Programming Language :: Python
Classifier: Topic :: Software Development :: Libraries :: Python Modules
